greenfootprint/__init__.py
greenfootprint/analyzer.py
greenfootprint/cli.py
greenfootprint-0.1.4.dist-info/licenses/LICENCE
greenfootprint-0.1.4.dist-info/METADATA
greenfootprint-0.1.4.dist-info/WHEEL
greenfootprint-0.1.4.dist-info/entry_points.txt
greenfootprint-0.1.4.dist-info/top_level.txt
greenfootprint-0.1.4.dist-info/RECORD
