Metadata-Version: 2.4
Name: greenfootprint
Version: 0.1.4
Summary: Estimate energy and carbon footprint of Python scripts
Home-page: https://github.com/thuve-codes/greenfootprint
Author: Thuverakan Tharumakulasooriyan
Author-email: thuverakantharma@gmail.com
Classifier: Programming Language :: Python :: 3
Classifier: License :: OSI Approved :: MIT License
Classifier: Operating System :: OS Independent
Requires-Python: >=3.7
License-File: LICENCE
Requires-Dist: psutil
Dynamic: author
Dynamic: author-email
Dynamic: classifier
Dynamic: description
Dynamic: description-content-type
Dynamic: home-page
Dynamic: license-file
Dynamic: requires-dist
Dynamic: requires-python
Dynamic: summary
